py_vetlog_analyzer/database_connector.py
py_vetlog_analyzer/database_filter.py
py_vetlog_analyzer/filter_username.py
py_vetlog_analyzer/main.py
py_vetlog_analyzer-1.0.0.dist-info/entry_points.txt
py_vetlog_analyzer-1.0.0.dist-info/METADATA
py_vetlog_analyzer-1.0.0.dist-info/WHEEL
py_vetlog_analyzer-1.0.0.dist-info/RECORD
