Metadata-Version: 2.1
Name: py-vetlog-analyzer
Version: 1.0.0
Summary: MySQL database analyzer for Vetlog
Home-page: https://github.com/josdem/py-vetlog-analyzer
License: Apache 2.0
Author: Jose Morales
Author-email: contact@josdem.io
Requires-Python: >=3.11,<4.0
Classifier: License :: Other/Proprietary License
Classifier: Programming Language :: Python :: 3
Classifier: Programming Language :: Python :: 3.11
Classifier: Programming Language :: Python :: 3.12
Requires-Dist: black (>=24.4.2,<25.0.0)
Requires-Dist: coverage (>=7.5.3,<8.0.0)
Requires-Dist: mysql-connector-python (>=8.4.0,<9.0.0)
Requires-Dist: python-dotenv (>=1.0.1,<2.0.0)
Project-URL: Repository, https://github.com/josdem/py-vetlog-analyzer
